{
  "id": 14,
  "header": "ato-checklist",
  "topicList": [
    "Infrastructure 🛠",
    "ATO Indicators and Features 🕵️‍♀️",
    "Product / UX 🎮",
    "Customer Service ☎️",
    "Investigations & Response 🚑",
    "Automation 🤖",
    "Anti-Phishing 🎣"
  ],
  "itemGroups": [
    {
      "topic": "Infrastructure 🛠",
      "items": [
        {
          "title": "<p>Backend systems we rely on for detection and mitigation.</p>"
        },
        {
          "title": "[ ] General Rate Limiting"
        },
        {
          "title": "[ ] User Event / Authentication Logs"
        },
        {
          "title": "[ ] Device Identification (Cookie)"
        },
        {
          "title": "See reference like <a href=\"https://github.com/magoo/AuthTables\">AuthTables</a></li>\n</ul>"
        },
        {
          "title": "[ ] Browser Fingerprinting (No Cookie)"
        },
        {
          "title": "See <a href=\"https://amiunique.org/\">AmIUnique</a>, <a href=\"https://coveryourtracks.eff.org/\">Cover Your Tracks</a>"
        },
        {
          "title": "🚨 Do not mix with ads infra 🚨</li>\n</ul>"
        },
        {
          "title": "[ ] Device Verification (Email confirmation, SMS, Snail Mail)"
        },
        {
          "title": "[ ] Customer Session, Password Reset Workflows (Backend)"
        },
        {
          "title": "[ ] Link Shim"
        },
        {
          "title": "[ ] Leaked Credential Pipeline (Backend)"
        },
        {
          "title": "[ ] Scraping (Pastebin, torrents, etc)"
        },
        {
          "title": "[ ] D a R k W e B and UnDErGroUnD"
        },
        {
          "title": "[ ] Periodically accessible dumps"
        }
      ]
    },
    {
      "topic": "ATO Indicators and Features 🕵️‍♀️",
      "items": [
        {
          "title": "<p>This section describes useful data that often needs to be acquired externally. These can be used in automated classification or to decorate investigation workflows with correlating info. </p>"
        },
        {
          "title": "[ ] Known proxies, tor, vps &amp; colocation"
        },
        {
          "title": "[ ] Observed malicious or  compromised (Paid)"
        },
        {
          "title": "[ ] Known Leaked Credentials"
        },
        {
          "title": "[ ] Recent Sim Swap"
        },
        {
          "title": "[ ] Domain intelligence"
        },
        {
          "title": "[ ] New domains"
        },
        {
          "title": "[ ] Disposable"
        },
        {
          "title": "[ ] Previously abused</li>\n</ul>"
        },
        {
          "title": "[ ] Address verification"
        },
        {
          "title": "[ ] Cellular verification (VoIP detection)"
        }
      ]
    },
    {
      "topic": "Product / UX 🎮",
      "items": [
        {
          "title": "<p>All user facing experiences to help reduce risk within a product.</p>"
        },
        {
          "title": "[ ] MFA Options"
        },
        {
          "title": "Security keys, MFA, SMS, backup codes, etc.</li>\n</ul>"
        },
        {
          "title": "[ ] Knowledge Base and self-support"
        },
        {
          "title": "Reducing outreach to support for questions.</li>\n</ul>"
        },
        {
          "title": "[ ] Link Shim"
        },
        {
          "title": "Allows for disabling of external links when copy-pasted, emailed, or otherwise brought off platform."
        },
        {
          "title": "Allows for warning messages before leaving platform.</li>\n</ul>"
        },
        {
          "title": "[ ] Victim and Witness escalation (Report Abuse)"
        },
        {
          "title": "Where victims of ATO report their issue."
        },
        {
          "title": "Where witnesses of abuse report off-platform impact of on-platform ATO.</li>\n</ul>"
        },
        {
          "title": "[ ] Forced Password Reset Workflows"
        },
        {
          "title": "[ ] Retroactively ask users to change leaked passwords"
        },
        {
          "title": "Existing customers will have weak passwords.</li>\n</ul>"
        },
        {
          "title": "[ ] Handle newly found customers from a leaked credential backend"
        },
        {
          "title": "Newly leaked credentials will cause a regular need to change customer passwords.</li>\n</ul>"
        },
        {
          "title": "[ ] \"Reset the password to your email\""
        },
        {
          "title": "Some investigations will indicate a customer's email is compromised, not their password.</li>\n</ul>"
        },
        {
          "title": "[ ] Account re-enable"
        },
        {
          "title": "Self service workflows to get back online after you have intervened.</li>\n</ul>\n</li>\n</ul>"
        },
        {
          "title": "[ ] Enforce <a href=\"https://github.com/dropbox/zxcvbn\">password strength</a> to prevent future weak passwords"
        },
        {
          "title": "[ ] New Registration"
        },
        {
          "title": "[ ] Password Change"
        },
        {
          "title": "[ ] Ongoing leaked / Newly weak</li>\n</ul>"
        },
        {
          "title": "[ ] Developer console prompts w/ a warning message"
        },
        {
          "title": "Example: <a href=\"https://security.stackexchange.com/questions/158106/facebooks-warning-of-self-xss\">Facebook</a></li>\n</ul>"
        },
        {
          "title": "[ ] Verification / Challenge workflows"
        },
        {
          "title": "When you are uncertain of the customer's location or device."
        },
        {
          "title": "[ ] SMS"
        },
        {
          "title": "[ ] Email"
        },
        {
          "title": "[ ] Account / Identity Knowledge"
        },
        {
          "title": "[ ] ID Submission"
        },
        {
          "title": "[ ] CAPTCHA"
        }
      ]
    },
    {
      "topic": "Customer Service ☎️",
      "items": [
        {
          "title": "<p>Operational customer service interactions (Support tickets). Support organizations often escalate abuse at scale to engineering and have the most visibility into what is, or is not, working.</p>"
        },
        {
          "title": "[ ] Standard Org Language"
        },
        {
          "title": "What counts as ATO?</li>\n</ul>"
        },
        {
          "title": "[ ] Metrics / KPI"
        },
        {
          "title": "Tracking abuse going up or down.</li>\n</ul>"
        },
        {
          "title": "[ ] IR Escalation"
        },
        {
          "title": "Playbooks / Plans for creating an outage or getting engineering resources involved.</li>\n</ul>"
        },
        {
          "title": "[ ] Reset Workflows (Administrative Frontends)"
        },
        {
          "title": "Empowering scalable operations to mitigate abuse scenarios."
        }
      ]
    },
    {
      "topic": "Investigations & Response 🚑",
      "items": [
        {
          "title": "<p>There will be periodic deep dives into ATO attacks to ask \"what happened?\". This section pertains to that perspective of work.</p>"
        },
        {
          "title": "[ ] Authentications are searchable by device, ip, user agent"
        },
        {
          "title": "[ ] Searches can pivot: Device to IP, IP to device, etc."
        },
        {
          "title": "[ ] Bonus: Actions / Events are searchable"
        },
        {
          "title": "[ ] Bonus: All routes / Endpoints are searchable</li>\n</ul>"
        },
        {
          "title": "[ ] Tooling exists to reset bulk accounts that meet criteria"
        },
        {
          "title": "[ ] Tooling exists to reverse transactions / changes that meet criteria."
        }
      ]
    },
    {
      "topic": "Automation 🤖",
      "items": [
        {
          "title": "<p>Tying everything together for operational ATO systems. Engineering time is the least scalable, customer support hours are more scalable, fully automated systems are the most scalable.</p>"
        },
        {
          "title": "[ ] Customer service classifies abuse cases"
        },
        {
          "title": "[ ] AI systems classifies authentication events"
        },
        {
          "title": "[ ] Suspicious cases push customers to verify activity"
        },
        {
          "title": "[ ] XFN meetings between groups to improve anti-abuse systematically"
        }
      ]
    },
    {
      "topic": "Anti-Phishing 🎣",
      "items": [
        {
          "title": "<p>Raising the bar against trivial credential stealing attacks which cause the most problems for unprepared organizations.</p>"
        },
        {
          "title": "[ ] SPF / DMARC / DKIM"
        },
        {
          "title": "[ ] Brand protection (Internet scanning for your brand being spoofed)"
        },
        {
          "title": "[ ] spoofed@ and customer phish reporting"
        },
        {
          "title": "[ ] App store hunting"
        },
        {
          "title": "[ ] Domain / ISP Takedowns"
        },
        {
          "title": "[ ] Browser blacklisting"
        },
        {
          "title": "[ ] Referer, hotlinks, adversary leaks"
        }
      ]
    }
  ],
  "sourceUrl": "https://example.com"
}